mcp_server_whisper/__init__.py
mcp_server_whisper/__main__.py
mcp_server_whisper/config.py
mcp_server_whisper/constants.py
mcp_server_whisper/exceptions.py
mcp_server_whisper/py.typed
mcp_server_whisper/server.py
mcp_server_whisper/domain/__init__.py
mcp_server_whisper/domain/audio_processor.py
mcp_server_whisper/domain/file_filter.py
mcp_server_whisper/infrastructure/__init__.py
mcp_server_whisper/infrastructure/cache.py
mcp_server_whisper/infrastructure/file_system.py
mcp_server_whisper/infrastructure/mcp_protocol.py
mcp_server_whisper/infrastructure/openai_client.py
mcp_server_whisper/infrastructure/path_resolver.py
mcp_server_whisper/models/__init__.py
mcp_server_whisper/models/audio.py
mcp_server_whisper/models/base.py
mcp_server_whisper/models/responses.py
mcp_server_whisper/models/transcription.py
mcp_server_whisper/models/tts.py
mcp_server_whisper/services/__init__.py
mcp_server_whisper/services/audio_service.py
mcp_server_whisper/services/file_service.py
mcp_server_whisper/services/transcription_service.py
mcp_server_whisper/services/tts_service.py
mcp_server_whisper/tools/__init__.py
mcp_server_whisper/tools/audio_tools.py
mcp_server_whisper/tools/file_tools.py
mcp_server_whisper/tools/transcription_tools.py
mcp_server_whisper/tools/tts_tools.py
mcp_server_whisper/utils/__init__.py
mcp_server_whisper/utils/text_utils.py
mcp_server_whisper-1.1.0.dist-info/METADATA
mcp_server_whisper-1.1.0.dist-info/WHEEL
mcp_server_whisper-1.1.0.dist-info/entry_points.txt
mcp_server_whisper-1.1.0.dist-info/licenses/LICENSE
mcp_server_whisper-1.1.0.dist-info/RECORD
