Metadata-Version: 2.4
Name: mcp-server-whisper
Version: 1.1.0
Summary: An MCP server for transcribing audio files using OpenAI Whisper and GPT-4o
Project-URL: Homepage, https://github.com/arcaputo3/mcp-server-whisper
Project-URL: Bug Tracker, https://github.com/arcaputo3/mcp-server-whisper/issues
Author-email: Richie Caputo <rcaputo3@tjclp.com>
License: MIT
License-File: LICENSE
Requires-Python: >=3.10
Requires-Dist: aiofiles>=25.1.0
Requires-Dist: aioresult
Requires-Dist: anyio
Requires-Dist: async-lru>=2.0.5
Requires-Dist: audioop-lts; python_version >= '3.13'
Requires-Dist: dotenv
Requires-Dist: ffmpeg-python
Requires-Dist: mcp>=1.17.0
Requires-Dist: openai>=2.4.0
Requires-Dist: pydantic-settings>=2.11.0
Requires-Dist: pydub
